LICENSE
README.md
setup.py
Karys_crazy_test.egg-info/PKG-INFO
Karys_crazy_test.egg-info/SOURCES.txt
Karys_crazy_test.egg-info/dependency_links.txt
Karys_crazy_test.egg-info/requires.txt
Karys_crazy_test.egg-info/top_level.txt
ciu/CIU.py
ciu/PerturbationMinMaxEstimator.py
ciu/__init__.py
ciu/ciuplots.py
ciu_tests/__init__.py
ciu_tests/ames_housing_gbm.py
ciu_tests/boston_gbm.py
ciu_tests/heart_disease_rf.py
ciu_tests/iris_lda.py
ciu_tests/titanic_rf.py